query_agent_benchmarking/__init__.py
query_agent_benchmarking/agent.py
query_agent_benchmarking/benchmark_run.py
query_agent_benchmarking/config.py
query_agent_benchmarking/create_benchmark.py
query_agent_benchmarking/database.py
query_agent_benchmarking/dataset.py
query_agent_benchmarking/models.py
query_agent_benchmarking/populate_db.py
query_agent_benchmarking/query_agent_benchmark.py
query_agent_benchmarking/utils.py
query_agent_benchmarking/metrics/ir_metrics.py
query_agent_benchmarking-0.3.dist-info/licenses/LICENSE
query_agent_benchmarking-0.3.dist-info/METADATA
query_agent_benchmarking-0.3.dist-info/WHEEL
query_agent_benchmarking-0.3.dist-info/top_level.txt
query_agent_benchmarking-0.3.dist-info/RECORD
